{
    "usd": [
        {
            "to": "eur",
            "value": 0.855066
        },
        {
            "to": "chf",
            "value": 0.916881
        },
        {
            "to": "jpy",
            "value": 109.799021
        },
        {
            "to": "gbp",
            "value": 0.733945
        }
    ],
    "eur": [
        {
            "to": "usd",
            "value" : 1.1695
        },
        {
            "to":"chf",
            "value": 1.072293
        },
        {
            "to":"jpy",
            "value": 128.431114
        },
        {
            "to":"gbp",
            "value": 0.858491
        }
    ],
    "chf": [
        {
            "to":"usd",
            "value": 1.090654
        },
        {
            "to":"eur",
            "value": 0.933366
        },
        {
            "to":"jpy",
            "value": 119.85351
        },
        {
            "to":"gbp",
            "value": 0.801154
        }
    ],
    "jpy": [
        {
            "to":"usd",
            "value": 0.009108
        },
        {
            "to":"eur",
            "value": 0.007787
        },
        {
            "to":"chf",
            "value": 0.008343
        },
        {
            "to":"gbp",
            "value": 0.006684
        }
    ],
    "gbp": [
        {
            "to":"usd",
            "value": 1.3625
        },
        {
            "to":"eur",
            "value": 1.164835
        },
        {
            "to":"chf",
            "value": 1.2482
        },
        {
            "to":"jpy",
            "value": 149.601077
        }

    ]
}